raccy/__init__.py
raccy/core/__init__.py
raccy/core/exceptions.py
raccy/core/meta.py
raccy/core/queue_.py
raccy/core/settings.py
raccy/core/signals.py
raccy/core/utils.py
raccy/utils/__init__.py
raccy/utils/driver.py
raccy/utils/utils.py
raccy/worker/__init__.py
raccy/worker/worker.py
raccy-2.0.0.dist-info/LICENSE
raccy-2.0.0.dist-info/METADATA
raccy-2.0.0.dist-info/WHEEL
raccy-2.0.0.dist-info/top_level.txt
raccy-2.0.0.dist-info/RECORD
