Metadata-Version: 2.1
Name: raccy
Version: 2.0.0
Summary: Web Scraping Library Based on Selenium
Home-page: https://github.com/danielafriyie/raccy
Author: Daniel Afriyie
Author-email: danielafriyie98@gmail.com
License: Apache License, Version 2.0
Platform: UNKNOWN
Classifier: Programming Language :: Python
Classifier: Programming Language :: Python :: 3
Classifier: Programming Language :: Python :: 3.6
Classifier: Programming Language :: Python :: 3.7
Classifier: Programming Language :: Python :: 3.8
Classifier: Intended Audience :: Developers
Classifier: Operating System :: OS Independent
Classifier: Topic :: Software Development :: Libraries :: Application Frameworks
Classifier: Topic :: Software Development :: Libraries :: Python Modules
Classifier: Development Status :: 5 - Production/Stable
Requires-Python: >=3.7
Requires-Dist: selenium (>=3.141.0)
Requires-Dist: wget (==3.2)
Requires-Dist: requests (==2.26.0)
Requires-Dist: raccy-orm (==0.0.1)
Requires-Dist: raccy-utils (==0.1.1)
